diffpy/__init__.py
diffpy/srfit/__init__.py
diffpy/srfit/exceptions.py
diffpy/srfit/version.py
diffpy/srfit/equation/__init__.py
diffpy/srfit/equation/builder.py
diffpy/srfit/equation/equationmod.py
diffpy/srfit/equation/literals/__init__.py
diffpy/srfit/equation/literals/abcs.py
diffpy/srfit/equation/literals/argument.py
diffpy/srfit/equation/literals/literal.py
diffpy/srfit/equation/literals/operators.py
diffpy/srfit/equation/visitors/__init__.py
diffpy/srfit/equation/visitors/argfinder.py
diffpy/srfit/equation/visitors/printer.py
diffpy/srfit/equation/visitors/swapper.py
diffpy/srfit/equation/visitors/validator.py
diffpy/srfit/equation/visitors/visitor.py
diffpy/srfit/fitbase/__init__.py
diffpy/srfit/fitbase/calculator.py
diffpy/srfit/fitbase/configurable.py
diffpy/srfit/fitbase/constraint.py
diffpy/srfit/fitbase/fitcontribution.py
diffpy/srfit/fitbase/fithook.py
diffpy/srfit/fitbase/fitrecipe.py
diffpy/srfit/fitbase/fitresults.py
diffpy/srfit/fitbase/parameter.py
diffpy/srfit/fitbase/parameterset.py
diffpy/srfit/fitbase/profile.py
diffpy/srfit/fitbase/profilegenerator.py
diffpy/srfit/fitbase/profileparser.py
diffpy/srfit/fitbase/recipeorganizer.py
diffpy/srfit/fitbase/restraint.py
diffpy/srfit/fitbase/simplerecipe.py
diffpy/srfit/fitbase/validatable.py
diffpy/srfit/interface/__init__.py
diffpy/srfit/interface/interface.py
diffpy/srfit/pdf/__init__.py
diffpy/srfit/pdf/basepdfgenerator.py
diffpy/srfit/pdf/characteristicfunctions.py
diffpy/srfit/pdf/debyepdfgenerator.py
diffpy/srfit/pdf/pdfcontribution.py
diffpy/srfit/pdf/pdfgenerator.py
diffpy/srfit/pdf/pdfparser.py
diffpy/srfit/sas/__init__.py
diffpy/srfit/sas/prcalculator.py
diffpy/srfit/sas/sasgenerator.py
diffpy/srfit/sas/sasimport.py
diffpy/srfit/sas/sasparameter.py
diffpy/srfit/sas/sasparser.py
diffpy/srfit/sas/sasprofile.py
diffpy/srfit/structure/__init__.py
diffpy/srfit/structure/basestructureparset.py
diffpy/srfit/structure/bvsrestraint.py
diffpy/srfit/structure/cctbxparset.py
diffpy_srfit-3.2.0.dist-info/licenses/AUTHORS.rst
diffpy_srfit-3.2.0.dist-info/licenses/LICENSE.rst
diffpy_srfit-3.2.0.dist-info/licenses/LICENSE_DANSE.rst
diffpy_srfit-3.2.0.dist-info/METADATA
diffpy_srfit-3.2.0.dist-info/WHEEL
diffpy_srfit-3.2.0.dist-info/top_level.txt
diffpy_srfit-3.2.0.dist-info/RECORD
