Metadata-Version: 2.4
Name: diffpy.srfit
Version: 3.2.0
Summary: Configurable code for solving atomic structures.
Author-email: Simon Billinge <sb2896@columbia.edu>
Maintainer-email: Simon Billinge <sb2896@columbia.edu>
Project-URL: Homepage, https://github.com/diffpy/diffpy.srfit/
Project-URL: Issues, https://github.com/diffpy/diffpy.srfit/issues/
Keywords: regression,modelling,fitting,diffraction,PDF
Classifier: Development Status :: 5 - Production/Stable
Classifier: Environment :: Console
Classifier: Intended Audience :: Developers
Classifier: Intended Audience :: Science/Research
Classifier: License :: Free To Use But Restricted
Classifier: Operating System :: MacOS :: MacOS X
Classifier: Operating System :: Microsoft :: Windows
Classifier: Operating System :: POSIX
Classifier: Operating System :: Unix
Classifier: Programming Language :: Python :: 3.11
Classifier: Programming Language :: Python :: 3.12
Classifier: Programming Language :: Python :: 3.13
Classifier: Topic :: Scientific/Engineering :: Physics
Classifier: Topic :: Scientific/Engineering :: Chemistry
Requires-Python: <3.14,>=3.11
License-File: LICENSE.rst
License-File: LICENSE_DANSE.rst
License-File: AUTHORS.rst
Requires-Dist: matplotlib
Requires-Dist: numpy
Requires-Dist: scipy
Dynamic: license-file
